LICENSE.rst
README.md
setup.cfg
setup.py
thePerfectlyJustSociety/__init__.py
thePerfectlyJustSociety/cli.py
thePerfectlyJustSociety/server.py
thePerfectlyJustSociety.egg-info/PKG-INFO
thePerfectlyJustSociety.egg-info/SOURCES.txt
thePerfectlyJustSociety.egg-info/dependency_links.txt
thePerfectlyJustSociety.egg-info/requires.txt
thePerfectlyJustSociety.egg-info/top_level.txt
thePerfectlyJustSociety/coinFlip/__init__.py
thePerfectlyJustSociety/coinFlip/coinFlip.py
thePerfectlyJustSociety/coinFlip/flipManager.py
thePerfectlyJustSociety/coinFlip/flips.py
thePerfectlyJustSociety/coinFlip/pollableThread.py
thePerfectlyJustSociety/coinFlip/population.py
thePerfectlyJustSociety/webapp/__init__.py
thePerfectlyJustSociety/webapp/appTestSpace.py
thePerfectlyJustSociety/webapp/dropdownOption.py
thePerfectlyJustSociety/webapp/explanation.py
thePerfectlyJustSociety/webapp/layout.py
thePerfectlyJustSociety/webapp/main.py
thePerfectlyJustSociety/webapp/progress.py
thePerfectlyJustSociety/webapp/screen.py
thePerfectlyJustSociety/webapp/style.py