Metadata-Version: 2.1
Name: thePerfectlyJustSociety
Version: 1.0.3
Summary: UNKNOWN
Home-page: https://github.com/ryanlague/thePerfectlyJustSociety
Author: Ryan Lague
Author-email: ryanlague@hotmail.com
License: MIT
Platform: UNKNOWN
License-File: LICENSE.rst
